interest_rate_swap_analyzer/__init__.py
interest_rate_swap_analyzer/analyzer.py
interest_rate_swap_analyzer/cli.py
interest_rate_swap_analyzer/swaps.py
interest_rate_swap_analyzer-1.0.0.dist-info/METADATA
interest_rate_swap_analyzer-1.0.0.dist-info/WHEEL
interest_rate_swap_analyzer-1.0.0.dist-info/entry_points.txt
interest_rate_swap_analyzer-1.0.0.dist-info/top_level.txt
interest_rate_swap_analyzer-1.0.0.dist-info/RECORD
