Metadata-Version: 2.2
Name: interest-rate-swap-analyzer
Version: 1.0.0
Summary: A tool to analyze interest rate swaps
Home-page: https://github.com/chrislawson-au/interest-rate-swap-analyzer
Author: Christopher Lawson
Author-email: 117199342+chrislawson-au@users.noreply.github.com
Classifier: Development Status :: 4 - Beta
Classifier: Programming Language :: Python :: 3
Classifier: Programming Language :: Python :: 3.6
Classifier: Programming Language :: Python :: 3.7
Classifier: Programming Language :: Python :: 3.8
Classifier: Programming Language :: Python :: 3.9
Classifier: License :: OSI Approved :: MIT License
Classifier: Operating System :: OS Independent
Classifier: Topic :: Office/Business :: Financial
Requires-Python: >=3.6
Requires-Dist: pandas>=1.0.0
Requires-Dist: matplotlib>=3.0.0
Requires-Dist: plotly>=5.0.0
Requires-Dist: numpy>=1.19.0
Provides-Extra: dev
Requires-Dist: pytest>=6.0.0; extra == "dev"
Requires-Dist: pytest-cov>=2.0.0; extra == "dev"
Requires-Dist: black>=22.0.0; extra == "dev"
Requires-Dist: flake8>=3.9.0; extra == "dev"
Dynamic: author
Dynamic: author-email
Dynamic: classifier
Dynamic: description
Dynamic: description-content-type
Dynamic: home-page
Dynamic: provides-extra
Dynamic: requires-dist
Dynamic: requires-python
Dynamic: summary
